<?xml version="1.0" encoding="UTF-8"?>

<Location xmlns="http://hl7.org/fhir">
  <id value="specialty-rx-location-1"/>
  <meta>
    <profile value="http://hl7.org/fhir/us/ncpdp/StructureDefinition/specialty-rx-location"/>
  </meta>
  <text>
    <status value="generated"/><div xmlns="http://www.w3.org/1999/xhtml"><p><b>Generated Narrative with Details</b></p><p><b>id</b>: specialty-rx-location-1</p><p><b>meta</b>: </p><p><b>status</b>: active</p><p><b>name</b>: Our Clinic - West Metro Office</p><p><b>mode</b>: instance</p><p><b>telecom</b>: ph: 555-555-5555, fax: 555-555-1234</p><p><b>address</b>: 10024 Minnetonka Blvd Suite 100 Minnetonka MN 55345 </p><p><b>managingOrganization</b>: <a href="Organization-specialty-rx-provider-organization-1.html">Our Clinics. Generated Summary: id: specialty-rx-provider-organization-1; 1669519278; active; <span title="Codes: {http://terminology.hl7.org/CodeSystem/organization-type prov}">Healthcare Provider</span>; name: Our Clinics; ph: 952-555-5555, contac-our-clinict@example.org</a></p></div>
  </text>
  <status value="active"/>
  <name value="Our Clinic - West Metro Office"/>
  <mode value="instance"/>
  <telecom>
    <system value="phone"/>
    <value value="555-555-5555"/>
  </telecom>
  <telecom>
    <system value="fax"/>
    <value value="555-555-1234"/>
  </telecom>
  <address>
    <line value="10024 Minnetonka Blvd"/>
    <line value="Suite 100"/>
    <city value="Minnetonka"/>
    <state value="MN"/>
    <postalCode value="55345"/>
  </address>
  <managingOrganization>
    <reference value="Organization/specialty-rx-provider-organization-1"/>
    <display value="Our Clinics"/>
  </managingOrganization>
</Location>